{
	"description": "项目配置文件。",
	"setting": {
		"urlCheck": false,
		"es6": true,
		"postcss": true,
		"minified": true,
		"newFeature": true
	},
	"miniprogramRoot": "dist/",
	"compileType": "miniprogram",
	"appid": "wx38b261fc1156dede",
	"projectname": "BlackMarket",
	"libVersion": "2.2.1",
	"condition": {
		"search": {
			"current": -1,
			"list": []
		},
		"conversation": {
			"current": -1,
			"list": []
		},
		"plugin": {
			"current": -1,
			"list": []
		},
		"game": {
			"currentL": -1,
			"list": []
		},
		"miniprogram": {
			"current": 1,
			"list": [
				{
					"id": -1,
					"name": "我的页面",
					"pathName": "pages/my/main",
					"query": "a=1&b=2&c=3&d=4",
					"scene": null
				},
				{
					"id": -1,
					"name": "分类",
					"pathName": "pages/index/main",
					"scene": null
				}
			]
		}
	}
}